LICENSE
MANIFEST.in
README.md
pyproject.toml
setup.cfg
setup.py
filerobot/__init__.py
filerobot/admin.py
filerobot/apps.py
filerobot/blocks.py
filerobot/constants.py
filerobot/fields.py
filerobot/forms.py
filerobot/models.py
filerobot/signals.py
filerobot/tests.py
filerobot/value.py
filerobot/wagtail_hooks.py
filerobot/locale/nl/LC_MESSAGES/django.mo
filerobot/locale/nl/LC_MESSAGES/django.po
filerobot/migrations/0001_initial.py
filerobot/migrations/0002_alter_designstate_options.py
filerobot/migrations/__init__.py
filerobot/migrations/__pycache__/0001_initial.cpython-311.pyc
filerobot/migrations/__pycache__/0002_alter_designstate_options.cpython-311.pyc
filerobot/migrations/__pycache__/__init__.cpython-311.pyc
filerobot/static/filerobot/css/filerobot.css
filerobot/static/filerobot/css/filerobot_widget.css
filerobot/static/filerobot/js/LICENSE.txt
filerobot/static/filerobot/js/README.md
filerobot/static/filerobot/js/file_robot_widget.js
filerobot/static/filerobot/js/file_robot_widget_controller.js
filerobot/static/filerobot/js/filerobot.js
filerobot/templates/filerobot/blocks/filerobot.html
filerobot/templates/filerobot/widgets/file_robot_widget.html
filerobot/templatetags/filerobot.py
filerobot/templatetags/__pycache__/filerobot.cpython-311.pyc
filerobot/utils/__init__.py
filerobot/utils/casing.py
filerobot/utils/dictionary.py
filerobot/views/__init__.py
filerobot/views/image_chooser.py
filerobot/views/utils.py
filerobot/views/widget.py
filerobot/widgets/__init__.py
filerobot/widgets/filerobot.py
filerobot/widgets/obj.py
tests/__init__.py
tests/testapp/__init__.py
tests/testapp/manage.py
tests/testapp/core/__init__.py
tests/testapp/core/tests.py
tests/testapp/core/migrations/__init__.py
tests/testapp/testapp/__init__.py
tests/testapp/testapp/asgi.py
tests/testapp/testapp/settings.py
tests/testapp/testapp/urls.py
tests/testapp/testapp/wsgi.py
wagtail_filerobot.egg-info/PKG-INFO
wagtail_filerobot.egg-info/SOURCES.txt
wagtail_filerobot.egg-info/dependency_links.txt
wagtail_filerobot.egg-info/requires.txt
wagtail_filerobot.egg-info/top_level.txt